jithub/__init__.py
jithub/backends/__init__.py
jithub/backends/adexp.py
jithub/backends/izhikevich.py
jithub/backends/mat_nu.py
jithub/backends/numba_adexp.py
jithub-0.1.0.dist-info/LICENSE
jithub-0.1.0.dist-info/METADATA
jithub-0.1.0.dist-info/WHEEL
jithub-0.1.0.dist-info/top_level.txt
jithub-0.1.0.dist-info/RECORD
