Metadata-Version: 2.1
Name: jithub
Version: 0.1.0
Summary: A example Python package
Home-page: https://github.com/russelljjarvis/jit-hub
Author: Russell Jarvis
Author-email: russelljarvis@protonmail.com
License: UNKNOWN
Platform: UNKNOWN
